{
    "labelAnnotations": [
        {
            "mid": "/m/0bt9lr",
            "description": "dog",
            "score": 0.9801435,
            "topicality": 0.9801435
        },
        {
            "mid": "/m/01z5f",
            "description": "dog like mammal",
            "score": 0.9483746,
            "topicality": 0.9483746
        },
        {
            "mid": "/m/0kpmf",
            "description": "dog breed",
            "score": 0.9387445,
            "topicality": 0.9387445
        },
        {
            "mid": "/m/05zmzn1",
            "description": "street dog",
            "score": 0.8927909,
            "topicality": 0.8927909
        },
        {
            "mid": "/m/02xl47d",
            "description": "dog breed group",
            "score": 0.8295599,
            "topicality": 0.8295599
        },
        {
            "mid": "/m/01lrl",
            "description": "carnivoran",
            "score": 0.6689563,
            "topicality": 0.6689563
        },
        {
            "mid": "/m/0d7s3w",
            "description": "puppy",
            "score": 0.58876985,
            "topicality": 0.58876985
        },
        {
            "mid": "/m/0blw4s",
            "description": "huntaway",
            "score": 0.58617586,
            "topicality": 0.58617586
        },
        {
            "mid": "/m/02z4cp8",
            "description": "potcake dog",
            "score": 0.52859926,
            "topicality": 0.52859926
        },
        {
            "mid": "/m/0265rtm",
            "description": "sporting group",
            "score": 0.5268567,
            "topicality": 0.5268567
        }
    ],
    "imagePropertiesAnnotation": {
        "dominantColors": {
            "colors": [
                {
                    "color": {
                        "red": 215,
                        "green": 189,
                        "blue": 155
                    },
                    "score": 0.2120695,
                    "pixelFraction": 0.02687094
                },
                {
                    "color": {
                        "red": 197,
                        "green": 148,
                        "blue": 102
                    },
                    "score": 0.09227202,
                    "pixelFraction": 0.0074596936
                },
                {
                    "color": {
                        "red": 25,
                        "green": 24,
                        "blue": 22
                    },
                    "score": 0.02597597,
                    "pixelFraction": 0.04331435
                },
                {
                    "color": {
                        "red": 178,
                        "green": 153,
                        "blue": 124
                    },
                    "score": 0.16340053,
                    "pixelFraction": 0.030721104
                },
                {
                    "color": {
                        "red": 221,
                        "green": 186,
                        "blue": 139
                    },
                    "score": 0.1006585,
                    "pixelFraction": 0.007860753
                },
                {
                    "color": {
                        "red": 224,
                        "green": 179,
                        "blue": 133
                    },
                    "score": 0.08840194,
                    "pixelFraction": 0.0061763055
                },
                {
                    "color": {
                        "red": 149,
                        "green": 147,
                        "blue": 143
                    },
                    "score": 0.07548546,
                    "pixelFraction": 0.5502527
                },
                {
                    "color": {
                        "red": 126,
                        "green": 123,
                        "blue": 119
                    },
                    "score": 0.06318874,
                    "pixelFraction": 0.17117189
                },
                {
                    "color": {
                        "red": 138,
                        "green": 122,
                        "blue": 98
                    },
                    "score": 0.051409744,
                    "pixelFraction": 0.01275367
                },
                {
                    "color": {
                        "red": 195,
                        "green": 159,
                        "blue": 114
                    },
                    "score": 0.042019337,
                    "pixelFraction": 0.004010588
                }
            ]
        }
    },
    "cropHintsAnnotation": {
        "cropHints": [
            {
                "boundingPoly": {
                    "vertices": [
                        {},
                        {
                            "x": 639
                        },
                        {
                            "x": 639,
                            "y": 426
                        },
                        {
                            "y": 426
                        }
                    ]
                },
                "confidence": 0.79999995,
                "importanceFraction": 1
            }
        ]
    }
}