{
    "labelAnnotations": [
        {
            "mid": "/m/0bt9lr",
            "description": "dog",
            "score": 0.9820024,
            "topicality": 0.9820024
        },
        {
            "mid": "/m/039rzl",
            "description": "irish setter",
            "score": 0.95629334,
            "topicality": 0.95629334
        },
        {
            "mid": "/m/01z5f",
            "description": "dog like mammal",
            "score": 0.9516779,
            "topicality": 0.9516779
        },
        {
            "mid": "/m/0kpmf",
            "description": "dog breed",
            "score": 0.9286455,
            "topicality": 0.9286455
        },
        {
            "mid": "/m/039ndd",
            "description": "setter",
            "score": 0.8729964,
            "topicality": 0.8729964
        },
        {
            "mid": "/m/03ht9m",
            "description": "field spaniel",
            "score": 0.78731334,
            "topicality": 0.78731334
        },
        {
            "mid": "/m/02kysw",
            "description": "spaniel",
            "score": 0.7462669,
            "topicality": 0.7462669
        },
        {
            "mid": "/m/0d5yby",
            "description": "sussex spaniel",
            "score": 0.7255169,
            "topicality": 0.7255169
        },
        {
            "mid": "/m/02wbgd",
            "description": "english cocker spaniel",
            "score": 0.72061163,
            "topicality": 0.72061163
        },
        {
            "mid": "/m/01lrl",
            "description": "carnivoran",
            "score": 0.66865516,
            "topicality": 0.66865516
        }
    ],
    "imagePropertiesAnnotation": {
        "dominantColors": {
            "colors": [
                {
                    "color": {
                        "red": 80,
                        "green": 38,
                        "blue": 27
                    },
                    "score": 0.39386937,
                    "pixelFraction": 0.16960068
                },
                {
                    "color": {
                        "red": 204,
                        "green": 192,
                        "blue": 183
                    },
                    "score": 0.019128056,
                    "pixelFraction": 0.07592672
                },
                {
                    "color": {
                        "red": 117,
                        "green": 70,
                        "blue": 53
                    },
                    "score": 0.1666209,
                    "pixelFraction": 0.078860745
                },
                {
                    "color": {
                        "red": 54,
                        "green": 20,
                        "blue": 12
                    },
                    "score": 0.13200077,
                    "pixelFraction": 0.027980534
                },
                {
                    "color": {
                        "red": 43,
                        "green": 16,
                        "blue": 14
                    },
                    "score": 0.059334327,
                    "pixelFraction": 0.012022328
                },
                {
                    "color": {
                        "red": 152,
                        "green": 103,
                        "blue": 84
                    },
                    "score": 0.048230022,
                    "pixelFraction": 0.039716616
                },
                {
                    "color": {
                        "red": 135,
                        "green": 116,
                        "blue": 94
                    },
                    "score": 0.034132157,
                    "pixelFraction": 0.15013596
                },
                {
                    "color": {
                        "red": 105,
                        "green": 83,
                        "blue": 63
                    },
                    "score": 0.022953108,
                    "pixelFraction": 0.027551167
                },
                {
                    "color": {
                        "red": 67,
                        "green": 36,
                        "blue": 34
                    },
                    "score": 0.017961672,
                    "pixelFraction": 0.005009303
                },
                {
                    "color": {
                        "red": 168,
                        "green": 148,
                        "blue": 129
                    },
                    "score": 0.017851032,
                    "pixelFraction": 0.11965078
                }
            ]
        }
    },
    "cropHintsAnnotation": {
        "cropHints": [
            {
                "boundingPoly": {
                    "vertices": [
                        {},
                        {
                            "x": 639
                        },
                        {
                            "x": 639,
                            "y": 477
                        },
                        {
                            "y": 477
                        }
                    ]
                },
                "confidence": 0.79999995,
                "importanceFraction": 1
            }
        ]
    }
}