{
    "labelAnnotations": [
        {
            "mid": "/m/0bt9lr",
            "description": "dog",
            "score": 0.9511759,
            "topicality": 0.9511759
        },
        {
            "mid": "/m/0kpmf",
            "description": "dog breed",
            "score": 0.94282305,
            "topicality": 0.94282305
        },
        {
            "mid": "/m/01z5f",
            "description": "dog like mammal",
            "score": 0.9389962,
            "topicality": 0.9389962
        },
        {
            "mid": "/m/02xl47d",
            "description": "dog breed group",
            "score": 0.8933253,
            "topicality": 0.8933253
        },
        {
            "mid": "/m/05zmzn1",
            "description": "street dog",
            "score": 0.8753534,
            "topicality": 0.8753534
        },
        {
            "mid": "/m/01lrl",
            "description": "carnivoran",
            "score": 0.6383032,
            "topicality": 0.6383032
        },
        {
            "mid": "/m/0286819",
            "description": "formosan mountain dog",
            "score": 0.5716115,
            "topicality": 0.5716115
        },
        {
            "mid": "/m/0466lfh",
            "description": "corgi chihuahua",
            "score": 0.52602893,
            "topicality": 0.52602893
        },
        {
            "mid": "/m/04gbpqk",
            "description": "vulnerable native breeds",
            "score": 0.51761353,
            "topicality": 0.51761353
        },
        {
            "mid": "/m/0265rtm",
            "description": "sporting group",
            "score": 0.509609,
            "topicality": 0.509609
        }
    ],
    "imagePropertiesAnnotation": {
        "dominantColors": {
            "colors": [
                {
                    "color": {
                        "red": 59,
                        "green": 55,
                        "blue": 54
                    },
                    "score": 0.37005043,
                    "pixelFraction": 0.09814055
                },
                {
                    "color": {
                        "red": 224,
                        "green": 224,
                        "blue": 229
                    },
                    "score": 0.12831019,
                    "pixelFraction": 0.32638925
                },
                {
                    "color": {
                        "red": 83,
                        "green": 78,
                        "blue": 75
                    },
                    "score": 0.28405493,
                    "pixelFraction": 0.09515691
                },
                {
                    "color": {
                        "red": 202,
                        "green": 202,
                        "blue": 206
                    },
                    "score": 0.07592812,
                    "pixelFraction": 0.258245
                },
                {
                    "color": {
                        "red": 117,
                        "green": 115,
                        "blue": 110
                    },
                    "score": 0.07187819,
                    "pixelFraction": 0.09616922
                },
                {
                    "color": {
                        "red": 155,
                        "green": 154,
                        "blue": 153
                    },
                    "score": 0.02696133,
                    "pixelFraction": 0.07544355
                },
                {
                    "color": {
                        "red": 56,
                        "green": 53,
                        "blue": 72
                    },
                    "score": 0.012975551,
                    "pixelFraction": 0.00063935213
                },
                {
                    "color": {
                        "red": 33,
                        "green": 29,
                        "blue": 33
                    },
                    "score": 0.010930849,
                    "pixelFraction": 0.03255368
                },
                {
                    "color": {
                        "red": 95,
                        "green": 83,
                        "blue": 70
                    },
                    "score": 0.007565578,
                    "pixelFraction": 0.0015451009
                },
                {
                    "color": {
                        "red": 73,
                        "green": 56,
                        "blue": 44
                    },
                    "score": 0.003984055,
                    "pixelFraction": 0.00042623474
                }
            ]
        }
    },
    "cropHintsAnnotation": {
        "cropHints": [
            {
                "boundingPoly": {
                    "vertices": [
                        {},
                        {
                            "x": 639
                        },
                        {
                            "x": 639,
                            "y": 639
                        },
                        {
                            "y": 639
                        }
                    ]
                },
                "confidence": 0.79999995,
                "importanceFraction": 1
            }
        ]
    }
}