{
    "labelAnnotations": [
        {
            "mid": "/m/0bt9lr",
            "description": "dog",
            "score": 0.93874913,
            "topicality": 0.93874913
        },
        {
            "mid": "/m/0kpmf",
            "description": "dog breed",
            "score": 0.9386406,
            "topicality": 0.9386406
        },
        {
            "mid": "/m/01z5f",
            "description": "dog like mammal",
            "score": 0.8707656,
            "topicality": 0.8707656
        },
        {
            "mid": "/m/025tcp1",
            "description": "russell terrier",
            "score": 0.8063861,
            "topicality": 0.8063861
        },
        {
            "mid": "/m/01d7fl",
            "description": "jack russell terrier",
            "score": 0.80043155,
            "topicality": 0.80043155
        },
        {
            "mid": "/m/08t9c_",
            "description": "grass",
            "score": 0.7800396,
            "topicality": 0.7800396
        },
        {
            "mid": "/m/05mqq3",
            "description": "snout",
            "score": 0.64389896,
            "topicality": 0.64389896
        },
        {
            "mid": "/m/0d7s3w",
            "description": "puppy",
            "score": 0.6065747,
            "topicality": 0.6065747
        },
        {
            "mid": "/m/03yl64",
            "description": "companion dog",
            "score": 0.6042771,
            "topicality": 0.6042771
        },
        {
            "mid": "/m/01lrl",
            "description": "carnivoran",
            "score": 0.58612114,
            "topicality": 0.58612114
        }
    ],
    "imagePropertiesAnnotation": {
        "dominantColors": {
            "colors": [
                {
                    "color": {
                        "red": 55,
                        "green": 50,
                        "blue": 18
                    },
                    "score": 0.1272124,
                    "pixelFraction": 0.070759624
                },
                {
                    "color": {
                        "red": 242,
                        "green": 233,
                        "blue": 229
                    },
                    "score": 0.10162725,
                    "pixelFraction": 0.091116026
                },
                {
                    "color": {
                        "red": 81,
                        "green": 85,
                        "blue": 24
                    },
                    "score": 0.047977023,
                    "pixelFraction": 0.12259365
                },
                {
                    "color": {
                        "red": 215,
                        "green": 194,
                        "blue": 170
                    },
                    "score": 0.04546151,
                    "pixelFraction": 0.038761705
                },
                {
                    "color": {
                        "red": 103,
                        "green": 31,
                        "blue": 5
                    },
                    "score": 0.032002695,
                    "pixelFraction": 0.003837149
                },
                {
                    "color": {
                        "red": 129,
                        "green": 115,
                        "blue": 31
                    },
                    "score": 0.024009407,
                    "pixelFraction": 0.0675078
                },
                {
                    "color": {
                        "red": 36,
                        "green": 84,
                        "blue": 168
                    },
                    "score": 0.0155121805,
                    "pixelFraction": 0.004942768
                },
                {
                    "color": {
                        "red": 57,
                        "green": 89,
                        "blue": 143
                    },
                    "score": 0.004602116,
                    "pixelFraction": 0.003121748
                },
                {
                    "color": {
                        "red": 39,
                        "green": 54,
                        "blue": 80
                    },
                    "score": 0.0040383628,
                    "pixelFraction": 0.004487513
                },
                {
                    "color": {
                        "red": 62,
                        "green": 59,
                        "blue": 12
                    },
                    "score": 0.05032581,
                    "pixelFraction": 0.048191987
                }
            ]
        }
    },
    "cropHintsAnnotation": {
        "cropHints": [
            {
                "boundingPoly": {
                    "vertices": [
                        {},
                        {
                            "x": 399
                        },
                        {
                            "x": 399,
                            "y": 399
                        },
                        {
                            "y": 399
                        }
                    ]
                },
                "confidence": 0.79999995,
                "importanceFraction": 1
            }
        ]
    }
}